git_history_extraction/__init__.py
git_history_extraction-0.7.0.dist-info/WHEEL
git_history_extraction-0.7.0.dist-info/entry_points.txt
git_history_extraction-0.7.0.dist-info/METADATA
git_history_extraction-0.7.0.dist-info/RECORD
