Metadata-Version: 2.3
Name: git-history-extraction
Version: 0.7.0
Summary: Extract and analyze git commit history with support for filtering by trailers, date ranges, and AI-powered summarization for changelogs
Keywords: git,changelog,history,commit,trailers,ai,summarization,openai,gemini
Author: Michael Bianco
Author-email: Michael Bianco <mike@mikebian.co>
Requires-Dist: click>=8.0
Requires-Dist: gitpython>=3.1.0
Requires-Dist: structlog>=25.5.0
Requires-Dist: structlog-config>=0.5.0
Requires-Dist: toon-python>=0.1.0
Requires-Python: >=3.10
Project-URL: Repository, https://github.com/iloveitaly/git-history-extraction
